[
  {
    "_id": "1",
    "owner": "1",
    "name": "Serenity Springs Resort",
    "type": "Hotel",
    "description": "Experience refined elegance and impeccable service at our luxurious hotel, where every detail is meticulously crafted to exceed your expectations.",
    "location": {
      "street": "120 Maple Avenue",
      "city": "Springfield",
      "country": "United States",
      "zipcode": "12345"
    },
    "beds": 2,
    "baths": 1,
    "square_feet": 1500,
    "amenities": [
      "Wifi",
      "Full kitchen",
      "Washer & Dryer",
      "Free Parking",
      "Hot Tub",
      "24/7 Security",
      "Wheelchair Accessible",
      "Elevator Access",
      "Dishwasher",
      "Gym/Fitness Center",
      "Air Conditioning",
      "Balcony/Patio",
      "Smart TV",
      "Coffee Maker"
    ],
    "rates": {
      "weekly": 1100,
      "monthly": 4200
    },
    "seller_info": {
      "name": "John Smith",
      "email": "john.smith@example.com",
      "phone": "+15551234567"
    },
    "images": ["a1.jpg", "a2.jpg", "a3.jpg"],
    "is_featured": false,
    "createdAt": "2024-01-01T00:00:00.000Z",
    "updatedAt": "2024-01-01T00:00:00.000Z"
  },
  {
    "_id": "2",
    "owner": "1",
    "name": "Riverfront Retreats",
    "type": "Apartment",
    "description": "Escape to a haven of tranquility and relaxation in our boutique hotel, where personalized service and upscale amenities await.",
    "location": {
      "street": "45 Elm Street",
      "city": "Willowdale",
      "country": "Canada",
      "zipcode": "10001"
    },
    "beds": 1,
    "baths": 1,
    "square_feet": 1800,
    "amenities": [
      "Wifi",
      "Full kitchen",
      "Washer & Dryer",
      "Free Parking",
      "Hot Tub",
      "24/7 Security",
      "Wheelchair Accessible",
      "Elevator Access",
      "Dishwasher",
      "High-Speed Internet",
      "Air Conditioning",
      "Smart TV",
      "Outdoor Grill/BBQ"
    ],
    "rates": {
      "weekly": 1000,
      "monthly": 4000
    },
    "seller_info": {
      "name": "John Smith",
      "email": "john.smith@example.com",
      "phone": "+1(555)123-4567"
    },
    "images": ["b1.jpg", "b2.jpg", "b3.jpg"],
    "is_featured": false,
    "createdAt": "2024-01-02T00:00:00.000Z",
    "updatedAt": "2024-01-02T00:00:00.000Z"
  },
  {
    "_id": "3",
    "owner": "2",
    "name": "Oasis Vista Hotel",
    "type": "Hotel",
    "description": "Unwind in style and comfort at our beachfront resort, where breathtaking ocean views, world-class dining, and endless leisure activities await.",
    "location": {
      "street": "Oak Lane",
      "city": "Birchfield",
      "country": "United Kingdom",
      "zipcode": "90001"
    },
    "beds": 3,
    "baths": 2,
    "square_feet": 2200,
    "amenities": [
      "Wifi",
      "Full kitchen",
      "Washer & Dryer",
      "Free Parking",
      "Hot Tub",
      "24/7 Security",
      "Wheelchair Accessible",
      "Elevator Access",
      "Dishwasher",
      "Swimming Pool",
      "Gym/Fitness Center",
      "Air Conditioning",
      "Smart TV",
      "Coffee Maker"
    ],
    "rates": {
      "nightly": 200,
      "weekly": 750,
      "monthly": 3300
    },
    "seller_info": {
      "name": "Emily Johnson",
      "email": "emily.johnson@example.com",
      "phone": "+44123567890"
    },
    "images": ["c1.jpg", "c2.jpg", "c3.jpg"],
    "is_featured": false,
    "createdAt": "2024-01-03T00:00:00.000Z",
    "updatedAt": "2024-01-03T00:00:00.000Z"
  },
  {
    "_id": "4",
    "owner": "2",
    "name": "Sunrise Summit Lodge",
    "type": "Cottage Or Cabin",
    "description": "Embark on a journey of indulgence and rejuvenation at our spa resort, where serenity and wellness converge to create an unforgettable retreat.",
    "location": {
      "street": "123 Pine Street",
      "city": "Cedarville",
      "country": "Australia",
      "zipcode": "78701"
    },
    "beds": 1,
    "baths": 1,
    "square_feet": 900,
    "amenities": [
      "Fireplace",
      "Outdoor Grill/BBQ",
      "Balcony/Patio",
      "Coffee Maker"
    ],
    "rates": {
      "weekly": 2000
    },
    "seller_info": {
      "name": "Emily Johnson",
      "email": "emily.johnson@example.com",
      "phone": "+44123567890"
    },
    "images": ["d1.jpg", "d2.jpg", "d3.jpg"],
    "is_featured": false,
    "createdAt": "2024-01-04T00:00:00.000Z",
    "updatedAt": "2024-01-04T00:00:00.000Z"
  },
  {
    "_id": "5",
    "owner": "3",
    "name": "Mystic Meadows Inn",
    "type": "Hotel",
    "description": "Immerse yourself in the rich culture and vibrant energy of the city at our centrally located hotel, where every stay is an opportunity for adventure and exploration.",
    "location": {
      "street": "75 Birch Avenue",
      "city": "Maplewood",
      "country": "New Zealand",
      "zipcode": "60601"
    },
    "beds": 1,
    "baths": 1,
    "square_feet": 900,
    "amenities": [
      "High-Speed Internet",
      "Smart TV",
      "Air Conditioning",
      "Gym/Fitness Center",
      "Outdoor Grill/BBQ"
    ],
    "rates": {
      "weekly": 1100,
      "monthly": 4200
    },
    "seller_info": {
      "name": "Michael Brown",
      "email": "michael.brown@example.com",
      "phone": "+61212345678"
    },
    "images": ["e1.jpg", "e2.jpg", "e3.jpg"],
    "is_featured": true,
    "createdAt": "2024-01-05T00:00:00.000Z",
    "updatedAt": "2024-01-05T00:00:00.000Z"
  },
  {
    "_id": "6",
    "owner": "3",
    "name": "Birchwood Terrace",
    "type": "Flat",
    "description": "Experience the epitome of luxury and exclusivity at our five-star hotel, where opulent accommodations, gourmet dining, and personalized service redefine hospitality.",
    "location": {
      "street": "456 Cedar Boulevard",
      "city": "Oakmont",
      "country": "Ireland",
      "zipcode": "33101"
    },
    "beds": 4,
    "baths": 3,
    "square_feet": 2800,
    "amenities": [
      "Beach Access",
      "Swimming Pool",
      "Balcony/Patio",
      "Smart TV",
      "Outdoor Grill/BBQ"
    ],
    "rates": {
      "nightly": 500,
      "weekly": 2500
    },
    "seller_info": {
      "name": "Michael Brown",
      "email": "michael.brown@example.com",
      "phone": "+61212345678"
    },
    "images": ["f1.jpg", "f2.jpg", "f3.jpg"],
    "is_featured": true,
    "createdAt": "2024-01-06T00:00:00.000Z",
    "updatedAt": "2024-01-06T00:00:00.000Z"
  },
  {
    "_id": "7",
    "owner": "4",
    "name": "Brookside Villas",
    "type": "Cottage Or Cabin",
    "description": "Escape the ordinary and embrace the extraordinary at our eco-friendly resort, where sustainable practices and stunning natural surroundings create a truly immersive experience.",
    "location": {
      "street": "789 Willow Way",
      "city": "Brookside",
      "country": "Australia",
      "zipcode": "80201"
    },
    "beds": 2,
    "baths": 1,
    "square_feet": 1100,
    "amenities": [
      "Fireplace",
      "Outdoor Grill/BBQ",
      "Hiking Trails Access",
      "Pet-Friendly"
    ],
    "rates": {
      "nightly": 475,
      "weekly": 2000
    },
    "seller_info": {
      "name": "Sarah Lee",
      "email": "sarah.lee@example.com",
      "phone": "+33123456789"
    },
    "images": ["g1.jpg", "g2.jpg", "g3.jpg"],
    "is_featured": false,
    "createdAt": "2024-01-07T00:00:00.000Z",
    "updatedAt": "2024-01-07T00:00:00.000Z"
  },
  {
    "_id": "8",
    "owner": "5",
    "name": "Paradise Cove Hotel",
    "type": "Chalet",
    "description": "Elevate your stay with unparalleled comfort and convenience at our business hotel, where state-of-the-art facilities and seamless service cater to your every need.",
    "location": {
      "street": "321 Birch Street",
      "city": "Maple Valley",
      "country": "Australia",
      "zipcode": "81611"
    },
    "beds": 3,
    "baths": 2,
    "square_feet": 1800,
    "amenities": [
      "Ski Equipment Storage",
      "Fireplace",
      "Balcony/Patio",
      "Smart TV"
    ],
    "rates": {
      "nightly": 300,
      "weekly": 1100
    },
    "seller_info": {
      "name": "David Martinez",
      "email": "david.martinez@example.com",
      "phone": "+34123457789"
    },
    "images": ["h1.jpg", "h2.jpg", "h3.jpg"],
    "is_featured": false,
    "createdAt": "2024-01-08T00:00:00.000Z",
    "updatedAt": "2024-01-08T00:00:00.000Z"
  },
  {
    "_id": "9",
    "owner": "6",
    "name": "Sunflower Fields Lodge",
    "type": "House",
    "description": "Step into a world of timeless elegance and unparalleled luxury at our historic hotel, where heritage meets modern sophistication to create an unforgettable experience.",
    "location": {
      "street": "600 Cedar Street",
      "city": "Oakville",
      "country": "New Zealand",
      "zipcode": "80301"
    },
    "beds": 4,
    "baths": 3,
    "square_feet": 2400,
    "amenities": [
      "Mountain View",
      "Hiking Trails Access",
      "Air Conditioning",
      "Smart TV",
      "Outdoor Grill/BBQ"
    ],
    "rates": {
      "weekly": 1000,
      "monthly": 3800
    },
    "seller_info": {
      "name": "Jennifer Nguyen",
      "email": "jennifer.nguyen@example.com",
      "phone": "+11234567890"
    },
    "images": ["i1.jpg", "i2.jpg", "i3.jpg"],
    "is_featured": false,
    "createdAt": "2024-01-09T00:00:00.000Z",
    "updatedAt": "2024-01-09T00:00:00.000Z"
  },
  {
    "_id": "10",
    "owner": "2",
    "name": "Harborview Apartments",
    "type": "Apartment",
    "description": "Savor the flavors of the world at our culinary destination hotel, where gourmet dining experiences, local delicacies, and innovative cuisine take center stage.",
    "location": {
      "street": "123 Birch Lane",
      "city": "Elmwood",
      "country": "United Kingdom",
      "zipcode": "19101"
    },
    "beds": 2,
    "baths": 1,
    "square_feet": 1200,
    "amenities": [
      "High-Speed Internet",
      "Air Conditioning",
      "Smart TV",
      "Coffee Maker"
    ],
    "rates": {
      "weekly": 550,
      "monthly": 2100
    },
    "seller_info": {
      "name": "Emily Johnson",
      "email": "emily.johnson@example.com",
      "phone": "+44123567890"
    },
    "images": ["j1.jpg", "j2.jpg", "j3.jpg"],
    "is_featured": false,
    "createdAt": "2024-01-10T00:00:00.000Z",
    "updatedAt": "2024-01-10T00:00:00.000Z"
  }
]
